{
  "status": "success",
  "generated_at": "2026-03-27T16:46:58.501505+00:00",
  "registered_model_name": "btc-usdt-directional-classifier",
  "model_name": "XGBoost",
  "model_family": "xgb",
  "model_accuracy": 0.9583333333333334,
  "model_f1": 0.9333333333333333,
  "probability_up": 0.5039559602737427,
  "predicted_signal": "UP",
  "predicted_label": 1,
  "best_champion_name": "XGBoost",
  "best_champion_family": "xgb",
  "best_champion_version": "5",
  "feature_preprocessor": "standard_scaler",
  "features_normalized": true,
  "model_predictions": {
    "lstm": {
      "name": "LSTM",
      "family": "lstm",
      "source": "champion",
      "accuracy": 0.7291666666666666,
      "f1": 0.6285714285714286,
      "cv_accuracy": 0.7291666666666666,
      "cv_f1": 0.6285714285714286,
      "probability_up": 0.9999440908432007,
      "predicted_signal": "UP",
      "predicted_label": 1,
      "registry_version": "6",
      "registered_model_name": "btc-usdt-directional-classifier-lstm",
      "is_current_best": false
    },
    "mlp_sklearn": {
      "name": "MLPClassifier",
      "family": "mlp_sklearn",
      "source": "champion",
      "accuracy": 0.6666666666666666,
      "f1": 0.6,
      "cv_accuracy": 0.6666666666666666,
      "cv_f1": 0.6,
      "probability_up": 0.6415249705314636,
      "predicted_signal": "UP",
      "predicted_label": 1,
      "registry_version": "15",
      "registered_model_name": "btc-usdt-directional-classifier-mlp_sklearn",
      "is_current_best": false
    },
    "nn": {
      "name": "NN",
      "family": "nn",
      "source": "champion",
      "accuracy": 0.9583333333333334,
      "f1": 0.9285714285714286,
      "cv_accuracy": 0.9583333333333334,
      "cv_f1": 0.9285714285714286,
      "probability_up": 0.8149033784866333,
      "predicted_signal": "UP",
      "predicted_label": 1,
      "registry_version": "5",
      "registered_model_name": "btc-usdt-directional-classifier-nn",
      "is_current_best": false
    },
    "rf": {
      "name": "RandomForest",
      "family": "rf",
      "source": "champion",
      "accuracy": 0.9375,
      "f1": 0.9032258064516129,
      "cv_accuracy": 0.9375,
      "cv_f1": 0.9032258064516129,
      "probability_up": 0.5154792666435242,
      "predicted_signal": "UP",
      "predicted_label": 1,
      "registry_version": "5",
      "registered_model_name": "btc-usdt-directional-classifier-rf",
      "is_current_best": false
    },
    "transformer": {
      "name": "Transformer",
      "family": "transformer",
      "source": "champion",
      "accuracy": 0.7291666666666666,
      "f1": 0.6060606060606061,
      "cv_accuracy": 0.7291666666666666,
      "cv_f1": 0.6060606060606061,
      "probability_up": 0.5950827598571777,
      "predicted_signal": "UP",
      "predicted_label": 1,
      "registry_version": "7",
      "registered_model_name": "btc-usdt-directional-classifier-transformer",
      "is_current_best": false
    },
    "xgb": {
      "name": "XGBoost",
      "family": "xgb",
      "source": "champion",
      "accuracy": 0.9583333333333334,
      "f1": 0.9333333333333333,
      "cv_accuracy": 0.9583333333333334,
      "cv_f1": 0.9333333333333333,
      "probability_up": 0.5039559602737427,
      "predicted_signal": "UP",
      "predicted_label": 1,
      "registry_version": "5",
      "registered_model_name": "btc-usdt-directional-classifier-xgb",
      "is_current_best": true
    }
  },
  "reference_candle_timestamp": "2026-03-27T16:00:00+00:00",
  "target_candle_timestamp": "2026-03-27T17:00:00+00:00",
  "reference_open": 66084.41,
  "reference_close": 65898.71,
  "price_to_beat": 66084.41,
  "symbol": "BTC/USDT",
  "timeframe": "1h"
}