{
  "status": "success",
  "generated_at": "2026-04-19T20:53:41.542540+00:00",
  "registered_model_name": "btc-usdt-directional-classifier-market-hours",
  "model_name": "XGBoost",
  "model_family": "xgb",
  "model_accuracy": 0.9166666666666666,
  "model_f1": 0.9047619047619048,
  "probability_up": 0.5177761912345886,
  "predicted_signal": "UP",
  "predicted_label": 1,
  "best_champion_name": "XGBoost",
  "best_champion_family": "xgb",
  "best_champion_version": "12",
  "feature_preprocessor": "standard_scaler",
  "features_normalized": true,
  "model_predictions": {
    "lstm": {
      "name": "LSTM",
      "family": "lstm",
      "source": "champion",
      "accuracy": 0.5,
      "f1": 0.5714285714285714,
      "cv_accuracy": 0.5,
      "cv_f1": 0.5714285714285714,
      "probability_up": 0.7925862073898315,
      "predicted_signal": "UP",
      "predicted_label": 1,
      "registry_version": "15",
      "registered_model_name": "btc-usdt-directional-classifier-market-hours-lstm",
      "is_current_best": false
    },
    "mlp_sklearn": {
      "name": "MLPClassifier",
      "family": "mlp_sklearn",
      "source": "champion",
      "accuracy": 0.5,
      "f1": 0.42857142857142855,
      "cv_accuracy": 0.5,
      "cv_f1": 0.42857142857142855,
      "probability_up": 0.6311984062194824,
      "predicted_signal": "UP",
      "predicted_label": 1,
      "registry_version": "15",
      "registered_model_name": "btc-usdt-directional-classifier-market-hours-mlp_sklearn",
      "is_current_best": false
    },
    "nn": {
      "name": "NN",
      "family": "nn",
      "source": "champion",
      "accuracy": 0.4375,
      "f1": 0.49056603773584906,
      "cv_accuracy": 0.4375,
      "cv_f1": 0.49056603773584906,
      "probability_up": 0.9287838935852051,
      "predicted_signal": "UP",
      "predicted_label": 1,
      "registry_version": "15",
      "registered_model_name": "btc-usdt-directional-classifier-market-hours-nn",
      "is_current_best": false
    },
    "rf": {
      "name": "RandomForest",
      "family": "rf",
      "source": "champion",
      "accuracy": 0.4375,
      "f1": 0.509090909090909,
      "cv_accuracy": 0.4375,
      "cv_f1": 0.509090909090909,
      "probability_up": 0.5196422338485718,
      "predicted_signal": "UP",
      "predicted_label": 1,
      "registry_version": "11",
      "registered_model_name": "btc-usdt-directional-classifier-market-hours-rf",
      "is_current_best": false
    },
    "transformer": {
      "name": "Transformer",
      "family": "transformer",
      "source": "champion",
      "accuracy": 0.4375,
      "f1": 0.34146341463414637,
      "cv_accuracy": 0.4375,
      "cv_f1": 0.34146341463414637,
      "probability_up": 0.7919962406158447,
      "predicted_signal": "UP",
      "predicted_label": 1,
      "registry_version": "25",
      "registered_model_name": "btc-usdt-directional-classifier-market-hours-transformer",
      "is_current_best": false
    },
    "xgb": {
      "name": "XGBoost",
      "family": "xgb",
      "source": "champion",
      "accuracy": 0.9166666666666666,
      "f1": 0.9047619047619048,
      "cv_accuracy": 0.9166666666666666,
      "cv_f1": 0.9047619047619048,
      "probability_up": 0.5177761912345886,
      "predicted_signal": "UP",
      "predicted_label": 1,
      "registry_version": "12",
      "registered_model_name": "btc-usdt-directional-classifier-market-hours-xgb",
      "is_current_best": true
    }
  },
  "reference_candle_timestamp": "2026-04-19T20:00:00+00:00",
  "target_candle_timestamp": "2026-04-19T21:00:00+00:00",
  "reference_open": 74848.55,
  "reference_close": 74654.05,
  "price_to_beat": 74848.55,
  "symbol": "BTC/USDT",
  "timeframe": "1h",
  "workflow_name": "market-hours-hourly",
  "workflow_variant": "hourly_train_7am_7pm_et_predict_8am_8pm_et"
}